MOD16_JPL/MOD16.py
MOD16_JPL/VPD_factor.py
MOD16_JPL/__init__.py
MOD16_JPL/canopy_aerodynamic_resistance.py
MOD16_JPL/canopy_conductance.py
MOD16_JPL/constants.py
MOD16_JPL/correctance_factor.py
MOD16_JPL/fwet.py
MOD16_JPL/interception.py
MOD16_JPL/mod16.csv
MOD16_JPL/parameters.py
MOD16_JPL/potential_soil_evaporation.py
MOD16_JPL/soil_moisture_constraint.py
MOD16_JPL/tmin_factor.py
MOD16_JPL/transpiration.py
MOD16_JPL/version.txt
MOD16_JPL/wet_canopy_resistance.py
MOD16_JPL/wet_soil_evaporation.py
MOD16_JPL/MCD12C1/MCD12C1.py
MOD16_JPL/MCD12C1/__init__.py
MOD16_JPL/SEBAL/SEBAL.py
MOD16_JPL/SEBAL/__init__.py
MOD16_JPL/downscaling/__init__.py
MOD16_JPL/downscaling/downscaling.py
MOD16_JPL/downscaling/linear_downscale.py
MOD16_JPL/evapotranspiration_conversion/__init__.py
MOD16_JPL/evapotranspiration_conversion/evapotranspiration_conversion.py
MOD16_JPL/meteorology_conversion/__init__.py
MOD16_JPL/meteorology_conversion/meteorology_conversion.py
MOD16_JPL/penman_monteith/__init__.py
MOD16_JPL/penman_monteith/penman_monteith.py
MOD16_JPL/priestley_taylor/__init__.py
MOD16_JPL/priestley_taylor/priestley_taylor.py
MOD16_JPL/santanello/__init__.py
MOD16_JPL/santanello/santanello.py
MOD16_JPL/soil_heat_flux/__init__.py
MOD16_JPL/soil_heat_flux/soil_heat_flux.py
MOD16_JPL/vegetation_conversion/__init__.py
MOD16_JPL/vegetation_conversion/vegetation_conversion.py
MOD16_JPL/verma_net_radiation/__init__.py
MOD16_JPL/verma_net_radiation/verma_net_radiation.py
mod16_jpl-1.1.0.dist-info/LICENSE
mod16_jpl-1.1.0.dist-info/METADATA
mod16_jpl-1.1.0.dist-info/WHEEL
mod16_jpl-1.1.0.dist-info/top_level.txt
mod16_jpl-1.1.0.dist-info/RECORD
