Metadata-Version: 2.2
Name: MOD16-JPL
Version: 1.1.0
Summary: JPL implementation of the MOD16 evapotranspiration algorithm for high resolution instantaneous remote sensing imagery
Author-email: Gregory Halverson <gregory.h.halverson@jpl.nasa.gov>, Qiaozhen Mu <qiaozhen@ntsg.umt.edu>, Maosheng Zhao <zhao@ntsg.umt.edu>, "Steven W. Running" <swr@ntsg.umt.edu>, "Claire S. Villanueva-Weeks" <claire.s.villanueva-weeks@jpl.gov>
Project-URL: Homepage, https://github.com/JPL-Evapotranspiration-Algorithms/MOD16-JPL
Classifier: Programming Language :: Python :: 3
Classifier: Operating System :: OS Independent
Requires-Python: >=3.10
License-File: LICENSE
Requires-Dist: affine
Requires-Dist: astropy
Requires-Dist: geopandas
Requires-Dist: h5py
Requires-Dist: keras
Requires-Dist: matplotlib
Requires-Dist: numpy
Requires-Dist: pandas
Requires-Dist: pillow
Requires-Dist: pygeos
Requires-Dist: pyproj
Requires-Dist: pyresample
Requires-Dist: rasterio
Requires-Dist: rasters
Requires-Dist: requests
Requires-Dist: scikit-image
Requires-Dist: scipy
Requires-Dist: shapely
Requires-Dist: six
Requires-Dist: sun-angles
Requires-Dist: tensorflow
Requires-Dist: urllib3
Provides-Extra: dev
Requires-Dist: build; extra == "dev"
Requires-Dist: pytest>=6.0; extra == "dev"
Requires-Dist: pytest-cov; extra == "dev"
Requires-Dist: jupyter; extra == "dev"
Requires-Dist: pytest; extra == "dev"
Requires-Dist: twine; extra == "dev"
